pulp_glue/deb/__init__.py
pulp_glue/deb/context.py
pulp_glue/deb/py.typed
pulp_glue_deb-0.4.2.dist-info/METADATA
pulp_glue_deb-0.4.2.dist-info/WHEEL
pulp_glue_deb-0.4.2.dist-info/top_level.txt
pulp_glue_deb-0.4.2.dist-info/RECORD
